Gcs_file_dependency_monitor/__init__.py
Gcs_file_dependency_monitor/main.py
Gcs_file_dependency_monitor-0.1.dist-info/METADATA
Gcs_file_dependency_monitor-0.1.dist-info/WHEEL
Gcs_file_dependency_monitor-0.1.dist-info/entry_points.txt
Gcs_file_dependency_monitor-0.1.dist-info/top_level.txt
Gcs_file_dependency_monitor-0.1.dist-info/RECORD
