Metadata-Version: 2.1
Name: Gcs-file-dependency-monitor
Version: 0.1
Requires-Dist: google-cloud-storage
Requires-Dist: datetime
